README.md
setup.cfg
setup.py
ydl_binaries/__init__.py
ydl_binaries/ffmpeg.py
ydl_binaries/utils.py
ydl_binaries/ydl.py
ydl_binaries.egg-info/PKG-INFO
ydl_binaries.egg-info/SOURCES.txt
ydl_binaries.egg-info/dependency_links.txt
ydl_binaries.egg-info/entry_points.txt
ydl_binaries.egg-info/top_level.txt