Metadata-Version: 1.0
Name: ydl-binaries
Version: 1.1.9
Summary: A collection of scripts that will download and update binaries for youtube-dl and ffmpeg.
Home-page: https://github.com/kepoorhampond/ydl-binaries
Author: Kepoor Hampond
Author-email: kepoorh@gmail.com
License: UNLICENSE
Platform: UNKNOWN
